lagrange_workflow/__init__.py
lagrange_workflow/read_file.py
example_lagrange_workflow-0.1.0.dist-info/LICENSE
example_lagrange_workflow-0.1.0.dist-info/METADATA
example_lagrange_workflow-0.1.0.dist-info/WHEEL
example_lagrange_workflow-0.1.0.dist-info/top_level.txt
example_lagrange_workflow-0.1.0.dist-info/RECORD
