Metadata-Version: 2.1
Name: example-lagrange-workflow
Version: 0.1.0
Summary: Example lagrange PyPI (Python Package Index) Package
Home-page: https://github.com/szainalie/example_lagrange_workflow
Author: Sadegh Zeynali
Author-email: sadegh.z@gmail.com
License: UNKNOWN
Project-URL: Documentation, https://github.com/szainalie/example_lagrange_workflow
Project-URL: Bug Reports, https://github.com/szainalie/example_lagrange_workflow/issues
Project-URL: Source Code, https://github.com/szainalie/example_lagrange_workflow
Keywords: example,pypi,package
Platform: UNKNOWN
Classifier: Development Status :: 5 - Production/Stable
Classifier: Intended Audience :: Developers
Classifier: Topic :: Software Development :: Build Tools
Classifier: Programming Language :: Python :: 3
Classifier: Programming Language :: Python :: 3.6
Classifier: Programming Language :: Python :: 3.7
Classifier: Programming Language :: Python :: 3.8
Classifier: Programming Language :: Python :: 3.9
Classifier: Programming Language :: Python :: 3 :: Only
Classifier: License :: OSI Approved :: MIT License
Classifier: Operating System :: OS Independent
Requires-Python: >=3.6
License-File: LICENSE
Requires-Dist: apache-beam
Provides-Extra: dev
Requires-Dist: check-manifest ; extra == 'dev'
